README.txt
setup.cfg
setup.py
ObjectRoles.egg-info/PKG-INFO
ObjectRoles.egg-info/SOURCES.txt
ObjectRoles.egg-info/dependency_links.txt
ObjectRoles.egg-info/namespace_packages.txt
ObjectRoles.egg-info/requires.txt
ObjectRoles.egg-info/top_level.txt
ez_setup/README.txt
ez_setup/__init__.py
peak/__init__.py
peak/util/__init__.py
peak/util/roles.py