Metadata-Version: 1.0
Name: ObjectRoles
Version: 0.6X
Summary: DEPRECATED: please use the AddOns package instead
Home-page: http://pypi.python.org/pypi/ObjectRoles
Author: Phillip J. Eby
Author-email: peak@eby-sarna.com
License: PSF or ZPL
Platform: UNKNOWN
